wordocx/__init__.py
wordocx/addComment.py
wordocx/getComments.py
wordocx/parsedocx.py
wordocx/parsejson.py
wordocx/trackChanges.py
wordocx-1.0.5.dist-info/LICENSE
wordocx-1.0.5.dist-info/METADATA
wordocx-1.0.5.dist-info/WHEEL
wordocx-1.0.5.dist-info/top_level.txt
wordocx-1.0.5.dist-info/RECORD
