Metadata-Version: 2.1
Name: wordocx
Version: 1.0.5
Summary: A simple docx manipulation utility library
Home-page: https://github.com/deigott/wordocx
Author: Ashad Mohamed
Author-email: deigott@proton.me
Classifier: Programming Language :: Python :: 3
Classifier: License :: OSI Approved :: MIT License
Classifier: Operating System :: OS Independent
Requires-Python: >=3.6
License-File: LICENSE
Requires-Dist: python-docx >=0.8.10
Requires-Dist: docx2python >=1.27.0
